python_cli_builder/__init__.py
python_cli_builder/command.py
python_cli_builder-0.1.0.dist-info/LICENSE
python_cli_builder-0.1.0.dist-info/METADATA
python_cli_builder-0.1.0.dist-info/WHEEL
python_cli_builder-0.1.0.dist-info/RECORD
